[
    {
        "key": "sb",
        "value": "nPZcaEQOKKhMrh9S8O-b8M3t",
        "domain": "facebook.com",
        "path": "/",
        "hostOnly": false,
        "creation": "2025-08-14T13:01:04.121Z",
        "lastAccessed": "2025-08-14T13:01:04.121Z"
    },
    {
        "key": "ps_l",
        "value": "1",
        "domain": "facebook.com",
        "path": "/",
        "hostOnly": false,
        "creation": "2025-08-14T13:01:04.121Z",
        "lastAccessed": "2025-08-14T13:01:04.121Z"
    },
    {
        "key": "ps_n",
        "value": "1",
        "domain": "facebook.com",
        "path": "/",
        "hostOnly": false,
        "creation": "2025-08-14T13:01:04.121Z",
        "lastAccessed": "2025-08-14T13:01:04.121Z"
    },
    {
        "key": "datr",
        "value": "bVyKaJpc0zH2sF0XuppGZlLu",
        "domain": "facebook.com",
        "path": "/",
        "hostOnly": false,
        "creation": "2025-08-14T13:01:04.121Z",
        "lastAccessed": "2025-08-14T13:01:04.121Z"
    },
    {
        "key": "c_user",
        "value": "61576683940167",
        "domain": "facebook.com",
        "path": "/",
        "hostOnly": false,
        "creation": "2025-08-14T13:01:04.121Z",
        "lastAccessed": "2025-08-14T13:01:04.121Z"
    },
    {
        "key": "xs",
        "value": "41%3AVMCpFrKhmDiZiA%3A2%3A1753901599%3A-1%3A-1",
        "domain": "facebook.com",
        "path": "/",
        "hostOnly": false,
        "creation": "2025-08-14T13:01:04.121Z",
        "lastAccessed": "2025-08-14T13:01:04.121Z"
    },
    {
        "key": "pas",
        "value": "61576683940167%3AD6GYfBJsXE",
        "domain": "facebook.com",
        "path": "/",
        "hostOnly": false,
        "creation": "2025-08-14T13:01:04.121Z",
        "lastAccessed": "2025-08-14T13:01:04.121Z"
    },
    {
        "key": "vpd",
        "value": "v1%3B793x424x1.445365309715271",
        "domain": "facebook.com",
        "path": "/",
        "hostOnly": false,
        "creation": "2025-08-14T13:01:04.121Z",
        "lastAccessed": "2025-08-14T13:01:04.121Z"
    },
    {
        "key": "fr",
        "value": "1DeNDr6FMkcAw0jgt.AWftA--eEJ1eaEztXpQKXQ93BjGqe1bdtmKZyAFDRgY8FZ_3qBM.BoiGh_..AAA.0.0.BomGsR.AWfA2FsdGA-w2asSlpAkmvZhU-E",
        "domain": "facebook.com",
        "path": "/",
        "hostOnly": false,
        "creation": "2025-08-14T13:01:04.121Z",
        "lastAccessed": "2025-08-14T13:01:04.121Z"
    },
    {
        "key": "fbl_st",
        "value": "101231197%3BT%3A29246989",
        "domain": "facebook.com",
        "path": "/",
        "hostOnly": false,
        "creation": "2025-08-14T13:01:04.121Z",
        "lastAccessed": "2025-08-14T13:01:04.121Z"
    },
    {
        "key": "wl_cbv",
        "value": "v2%3Bclient_version%3A2889%3Btimestamp%3A1754819345",
        "domain": "facebook.com",
        "path": "/",
        "hostOnly": false,
        "creation": "2025-08-14T13:01:04.121Z",
        "lastAccessed": "2025-08-14T13:01:04.121Z"
    }
]
